godaddy_api/__about__.py
godaddy_api/__init__.py
godaddy_api/__main__.py
godaddy_api/godaddy_client.py
godaddy_api/py.typed
godaddy_api/data/domain_available.py
godaddy_api/data/domain_record.py
godaddy_api-0.0.1.dist-info/METADATA
godaddy_api-0.0.1.dist-info/WHEEL
godaddy_api-0.0.1.dist-info/licenses/LICENSE.txt
godaddy_api-0.0.1.dist-info/RECORD
